schemapack/__init__.py
schemapack/__main__.py
schemapack/cli.py
schemapack/exceptions.py
schemapack/plugins.py
schemapack/py.typed
schemapack/utils.py
schemapack/_internals/__init__.py
schemapack/_internals/dump.py
schemapack/_internals/erd.py
schemapack/_internals/exceptions.py
schemapack/_internals/isolate.py
schemapack/_internals/load.py
schemapack/_internals/main.py
schemapack/_internals/normalize.py
schemapack/_internals/utils.py
schemapack/_internals/cli/__init__.py
schemapack/_internals/cli/exception_handling.py
schemapack/_internals/cli/exit_codes.py
schemapack/_internals/cli/main.py
schemapack/_internals/cli/printing.py
schemapack/_internals/spec/__init__.py
schemapack/_internals/spec/base.py
schemapack/_internals/spec/custom_types.py
schemapack/_internals/spec/datapack.py
schemapack/_internals/spec/schemapack.py
schemapack/_internals/validation/__init__.py
schemapack/_internals/validation/_main.py
schemapack/_internals/validation/base.py
schemapack/_internals/validation/default.py
schemapack/_internals/validation/plugins/__init__.py
schemapack/_internals/validation/plugins/content_schema.py
schemapack/_internals/validation/plugins/expected_root.py
schemapack/_internals/validation/plugins/missing_class.py
schemapack/_internals/validation/plugins/missing_origin.py
schemapack/_internals/validation/plugins/missing_relations.py
schemapack/_internals/validation/plugins/missing_target.py
schemapack/_internals/validation/plugins/multiple_target.py
schemapack/_internals/validation/plugins/one_to_many_overlap.py
schemapack/_internals/validation/plugins/unexpected_root.py
schemapack/_internals/validation/plugins/unknown_class.py
schemapack/_internals/validation/plugins/unknown_relations.py
schemapack/spec/__init__.py
schemapack/spec/custom_types.py
schemapack/spec/datapack.py
schemapack/spec/schemapack.py
schemapack-4.0.1.dist-info/licenses/LICENSE
schemapack-4.0.1.dist-info/METADATA
schemapack-4.0.1.dist-info/WHEEL
schemapack-4.0.1.dist-info/entry_points.txt
schemapack-4.0.1.dist-info/top_level.txt
schemapack-4.0.1.dist-info/RECORD
