Metadata-Version: 2.4
Name: schemapack
Version: 4.0.1
Summary: Make your JSON Schemas sociable and create linked data models.
Author-email: "German Human Genome Phenome Archive (GHGA)" <contact@ghga.de>
License: Apache 2.0
Project-URL: Repository, https://github.com/ghga-de/schemapack
Classifier: Development Status :: 1 - Planning
Classifier: Operating System :: POSIX :: Linux
Classifier: Programming Language :: Python :: 3
Classifier: Programming Language :: Python :: 3.13
Classifier: License :: OSI Approved :: Apache Software License
Classifier: Topic :: Internet :: WWW/HTTP :: HTTP Servers
Classifier: Topic :: Software Development :: Libraries
Classifier: Intended Audience :: Developers
Requires-Python: >=3.12
License-File: LICENSE
Requires-Dist: pydantic<3,>=2
Requires-Dist: pydantic_settings<3,>=2
Requires-Dist: ruamel.yaml~=0.18.6
Requires-Dist: jsonschema<5,>=4.19.2
Requires-Dist: arcticfreeze~=0.1.1
Requires-Dist: rich<14,>13
Requires-Dist: typer>=0.16.0
Dynamic: license-file
